{"invoiceNumber": "1234", "date": "November 30, 2022", "billTo": {"customerName": "Henry Ross", "customerID": "8675309", "address": "123 Avenue A, Metropolis", "phone": "(123) 456-7890"}, "shipTo": {"recipientName": "Henry Ross", "address": "123 Avenue A, Metropolis", "phone": "(123) 456-7890"}, "paymentDue": "December 30, 2022", "deliveryDate": "December 7, 2022", "salesperson": "Luca Richter", "shippingMethod": "Ground", "paymentTerms": "Cash or check", "shippingTerms": "Returns not accepted", "items": [{"quantity": 10, "itemNumber": "123", "description": "Baby chicks", "unitPrice": 5.0, "discount": "10%", "lineTotal": 45.0}, {"quantity": 2, "itemNumber": "444", "description": "Heat lamps", "unitPrice": 24.0, "discount": null, "lineTotal": 48.0}, {"quantity": 6, "itemNumber": "120", "description": "Chicken roosts", "unitPrice": 30.0, "discount": null, "lineTotal": 180.0}], "totalDiscount": 5.0, "subtotal": 278.0, "salesTax": 13.9, "total": 286.9, "companyDetails": {"name": "Happiest Valley Farms", "address": "456 Anyroad, Anywhere", "website": "interestingsite.com", "phone": "(123) 987-6543", "fax": "(123) 987-6542", "email": "happiest@example.com"}}